{
  "replay_type": "wallet_telemetry",
  "attack_class": "poly_network_authority_takeover",

  "signer_metrics": {
    "expected_signers": 4,
    "observed_signers": 1,
    "signer_deviation_score": 0.96
  },

  "withdrawal_metrics": {
    "withdrawal_velocity_usd_per_min": 8200000
  },

  "entropy_metrics": {
    "transaction_entropy": 0.82
  },

  "timestamps": {
    "t0_detected": 0,
    "t1_authority": 9,
    "t2_velocity": 18,
    "t3_entropy": 29,
    "t4_event_horizon": 38
  },

  "meta": {
    "inspired_by": "PolyNetwork_2021"
  }
}
